<?xml version="1.0" encoding="UTF-8"?>
<!DOCTYPE mapper
        PUBLIC "-//mybatis.org//DTD Mapper 3.0//EN"
        "http://mybatis.org/dtd/mybatis-3-mapper.dtd">
<mapper namespace="com.sswh.dao.PlatformUserDao">
    <delete id="deleteByIds">
        delete from sswh.platformuser  WHERE iid IN
        <foreach item="item" index="index" collection="list" open="(" separator="," close=")">
            #{item}
        </foreach>
    </delete>
    <select id="findByIid"  resultMap="seeShare">
        SELECT iid, username, password, mobilephone, idcard, groupiid
        FROM sswh.platformuser
        <where>
            iid = #{iid}
        </where>
    </select>
    <insert id="registUser" parameterType="com.sswh.entity.PlatformUser">
        INSERT INTO sswh.platformuser(username, password, mobilephone, idcard, password_salt)
        VALUES(#{username},#{password},#{mobilePhone},#{idCard},#{passwordSalt});
    </insert>
    <select id="findByIids" resultMap="seeShare">
        SELECT iid, username, password, mobilephone, idcard FROM sswh.platformuser WHERE iid IN
        <foreach item="item" index="index" collection="list" open="(" separator="," close=")">
            #{item}
        </foreach>
    </select>
    <resultMap id="seeShare" type="com.sswh.entity.PlatformUser">
        <id column="iid" property="iid"/>
        <result column="username" property="username"/>
        <result column="groupiid" property="groupIid"/>
        <result column="password" property="password"/>
        <result column="mobilephone" property="mobilePhone"/>
        <result column="idcard" property="idCard"/>
        <result column="password_salt" property="passwordSalt"/>
    </resultMap>
    <!-- 插入物品信息 -->
    <insert id="registUsers"  parameterType="java.util.List">
        INSERT INTO sswh.platformuser
        (
        username, password, mobilephone, idcard, password_salt
        )
        VALUES
        <foreach collection="list" item="item" index="index" separator=",">
            (
            #{item.username},
            #{item.password},
            #{item.mobilePhone},
            #{item.idCard},
            #{item.passwordSalt}
            )
        </foreach>
    </insert>
    <select id="findByUsername" parameterType="java.lang.String" resultMap="seeShare">
        SELECT iid, username, password, mobilephone, idcard, password_salt
        FROM platformuser
        WHERE username like #{username}
    </select>
    <select id="findCountByUsername" parameterType="java.lang.String" resultType="int">
        SELECT count(*) FROM sswh.platformuser
        <where>
            <if test="_parameter != null">
                username like #{username}
            </if>
        </where>
    </select>
    <select id="findByIdCard" parameterType="java.lang.String" resultMap="seeShare">
        SELECT iid, username, password, mobilephone, idcard, password_salt
        FROM sswh.platformuser
        <where>
            <if test="_parameter != null">
                idcard = #{idCard}
            </if>
        </where>
    </select>
    <select id="findAllPlatformUser" resultType="com.sswh.entity.PlatformUser">
        SELECT iid, username, password, mobilephone, idcard, password_salt
         FROM sswh.platformuser
    </select>
    <select id="findAllByTitle" resultType="com.sswh.entity.PlatformUser">
        SELECT iid, username, password, mobilephone, idcard, password_salt
        FROM sswh.platformuser
        <where>
            <if test="_parameter != null">
                username = #{username}
            </if>
        </where>
    </select>
    <select id="queryAllByLimit" resultType="com.sswh.entity.PlatformUser">
        select
            iid, username, password, mobilephone, idcard, password_salt
        from sswh.platformuser
        limit #{offset}, #{limit}

    </select>
</mapper>
